{
  "_class": "group",
  "do_objectID": "5B53E350-4910-4906-99B7-448A592B8A93",
  "exportOptions": {
    "_class": "exportOptions",
    "exportFormats": [
    ],
    "includedLayerIds": [
    ],
    "layerOptions": 0,
    "shouldTrim": false
  },
  "frame": {
    "_class": "rect",
    "constrainProportions": false,
    "height": 15,
    "width": 63,
    "x": 9,
    "y": 0
  },
  "hasClickThrough": false,
  "isFlippedHorizontal": false,
  "isFlippedVertical": false,
  "isLocked": false,
  "isVisible": true,
  "layerListExpandedType": 2,
  "layers": [
    {
      "class": "group",
      "id": "0D002C5C-5A42-44E6-BE6E-F0D285D7E3E1"
    },
    {
      "class": "text",
      "id": "A08ED824-F34A-4054-85F7-40D59A005436"
    }
  ],
  "name": "Battery",
  "nameIsFixed": true,
  "resizingConstraint": 44,
  "resizingType": 1,
  "rotation": 0,
  "shouldBreakMaskChain": false,
  "style": {
    "_class": "style",
    "endDecorationType": 0,
    "miterLimit": 10,
    "startDecorationType": 0
  }
}